mypy_baseline/__init__.py
mypy_baseline/__main__.py
mypy_baseline/_cli.py
mypy_baseline/_colors.py
mypy_baseline/_config.py
mypy_baseline/_error.py
mypy_baseline/_git.py
mypy_baseline/py.typed
mypy_baseline/commands/__init__.py
mypy_baseline/commands/_base.py
mypy_baseline/commands/_filter.py
mypy_baseline/commands/_history.py
mypy_baseline/commands/_plot.py
mypy_baseline/commands/_suggest.py
mypy_baseline/commands/_sync.py
mypy_baseline/commands/_top_files.py
mypy_baseline/commands/_version.py
mypy_baseline-0.7.3.dist-info/entry_points.txt
mypy_baseline-0.7.3.dist-info/LICENSE
mypy_baseline-0.7.3.dist-info/WHEEL
mypy_baseline-0.7.3.dist-info/METADATA
mypy_baseline-0.7.3.dist-info/RECORD
