Metadata-Version: 2.1
Name: mypy_baseline
Version: 0.7.3
Summary: Integrate mypy with existing codebase.
Keywords: mypy,baseline,typing,annotations,type annotations
Author-email: Gram <git@orsinium.dev>
Requires-Python: >=3.9
Classifier: Development Status :: 5 - Production/Stable
Classifier: Intended Audience :: Developers
Classifier: License :: OSI Approved :: MIT License
Classifier: Programming Language :: Python
Classifier: Typing :: Typed
Requires-Dist: sphinx ; extra == "docs"
Requires-Dist: myst-parser ; extra == "docs"
Requires-Dist: flake8 ; extra == "lint"
Requires-Dist: isort ; extra == "lint"
Requires-Dist: mypy ; extra == "lint"
Requires-Dist: types-requests ; extra == "lint"
Requires-Dist: types-toml ; extra == "lint"
Requires-Dist: pytest ; extra == "test"
Requires-Dist: pytest-cov ; extra == "test"
Requires-Dist: requests ; extra == "test"
Requires-Dist: responses ; extra == "test"
Project-URL: Source, https://github.com/orsinium-labs/mypy-baseline
Provides-Extra: docs
Provides-Extra: lint
Provides-Extra: test
